da_vis/__init__.py
da_vis/visualizer.py
da_vis/plots/__init__.py
da_vis/plots/correlation.py
da_vis/plots/dimensionality_reduction.py
da_vis/plots/distribution.py
da_vis/plots/feature_importance.py
da_vis/plots/performance.py
da_vis/utils/__init__.py
da_vis/utils/data_loader.py
da_vis/utils/plot_helpers.py
da_viz-0.1.dist-info/LICENCE
da_viz-0.1.dist-info/METADATA
da_viz-0.1.dist-info/WHEEL
da_viz-0.1.dist-info/top_level.txt
da_viz-0.1.dist-info/RECORD
