Metadata-Version: 2.1
Name: da_viz
Version: 0.1
Summary: A package for visualizing data and machine learning model performance
Home-page: https://github.com/mixter3011/da_vis.git
Author: Sabyasachi
Author-email: sabychakraborty08@gmail.com
Classifier: Programming Language :: Python :: 3
Classifier: License :: OSI Approved :: MIT License
Classifier: Operating System :: OS Independent
Requires-Python: >=3.6
License-File: LICENCE
Requires-Dist: matplotlib
Requires-Dist: seaborn
Requires-Dist: scikit-learn
Requires-Dist: shap
Requires-Dist: pandas
Requires-Dist: dash
Requires-Dist: plotly
